[{"id":1570,"nome":"Lead WhatsApp","telefone":"554791917605","status":"received","criado_em":"2026-04-25T18:00:27.779608+00:00"}, 
 {"id":1569,"nome":"Dalva","telefone":"554797283991","status":"received","criado_em":"2026-04-25T16:00:27.89841+00:00"}, 
 {"id":1568,"nome":"Sergio","telefone":"5547984860080","status":"received","criado_em":"2026-04-25T13:00:25.499004+00:00"}, 
 {"id":1566,"nome":"Lead WhatsApp","telefone":"554991486782","status":"received","criado_em":"2026-04-24T22:00:28.553884+00:00"}, 
 {"id":1567,"nome":"Cristiano Loch","telefone":"554792777642","status":"received","criado_em":"2026-04-24T22:00:28.553884+00:00"}]
